Workbook

Sheet Zonelark FCA Log
A1: Fixed ID Number | B1: Facility Name | C1: Facility Type/Usage | D1: Facility Level/Floor | E1: Room Number | F1: Room Name | G1: Area / Asset Served | H1: Asset / CMMS ID (e.g. TAG #) | I1: Asset Name (e.g. AHU-3) | J1: Asset Manufacturer | K1: Asset Model Number | L1: Asset Serial Number | M1: Asset Approximate Install Year | N1: Notes/Comments | O1: FCA 1-5 | P1: Asset Type | Q1: Asset "Size" | R1: Asset Quantity Multiplier | S1: Unit of Measure | T1: Asset Repair or Replace | U1: Uniformat Level 2 | V1: Industry Life Expectancy | W1: Industry Replacement Year | X1: Industry Life Remaining | Y1: Estimated / Observed Life Remaining | Z1: Observed Replacement Year | AA1: Unit Probable Cost ($) (MANUAL ENTRY POSSIBLE) | AB1: Extended Probable Cost ($) | AC1: Depreciated Value | AD1: Annual Maintenance | AE1: Facility Square Feet | AF1: Date of Assessment | AG1: Operational Impact (1-5) | AH1: Energy Impact (1-5)
A2: 01 | B2: Riverside Medical Center | C2: Healthcare | D2: Basement | E2: B-101 | F2: Mechanical Room | G2: ICU Wing / OR Suite | H2: AHU-001 | I2: AHU-1 | J2: Carrier | K2: 39MBB030 | L2: 2918KA07263 | M2: 2008 | N2: Minor corrosion on drain pan. Filter housing bent. | O2: 3 | P2: Air Handling Unit | Q2: 30 Ton | R2: 1 | S2: EA | T2: Repair | U2: D30 HVAC | V2: 20 | W2: =M2+V2 | X2: =W2-2026 | Y2: 4 | Z2: 2030 | AA2: 18000 | AB2: =R2*AA2 | AC2: =IF(20>0,AB2*MAX(0,X2)/20,0) | AD2: =AB2*0.03 | AE2: 85000 | AF2: 2026-06-25 | AG2: 5 | AH2: 5
A3: 01 | B3: Riverside Medical Center | C3: Healthcare | D3: Roof Level | E3: R-01 | F3: Rooftop Mechanical | G3: Admin Wing | H3: RTU-002 | I3: RTU-2 | J3: Lennox | K3: LGH240H4BM1G | L3: 5820H24568 | M3: 2015 | N3: Economizer damper seized. Refrigerant charge OK. | O3: 2 | P3: Packaged Rooftop Unit | Q3: 20 Ton | R3: 1 | S3: EA | T3: Repair | U3: D30 HVAC | V3: 15 | W3: =M3+V3 | X3: =W3-2026 | Y3: 2 | Z3: 2028 | AA3: 22000 | AB3: =R3*AA3 | AC3: =IF(15>0,AB3*MAX(0,X3)/15,0) | AD3: =AB3*0.03 | AE3: 85000 | AF3: 2026-06-25 | AG3: 4 | AH3: 5
A4: 01 | B4: Riverside Medical Center | C4: Healthcare | D4: Basement | E4: B-102 | F4: Boiler Room | G4: Perimeter Radiation / Domestic HW | H4: BLRP-001 | I4: BLR-1 | J4: Cleaver-Brooks | K4: ClearFire-C CF-200 | L4: CB-20213847 | M4: 2012 | N4: Annual service completed. Burner assembly cleaned. | O4: 4 | P4: Boiler | Q4: 200 BHP | R4: 2 | S4: EA | T4: Maintain | U4: D30 HVAC | V4: 25 | W4: =M4+V4 | X4: =W4-2026 | Y4: 11 | Z4: 2037 | AA4: 48000 | AB4: =R4*AA4 | AC4: =IF(25>0,AB4*MAX(0,X4)/25,0) | AD4: =AB4*0.02 | AE4: 85000 | AF4: 2026-06-25 | AG4: 5 | AH4: 4
A5: 02 | B5: Riverside Medical Center | C5: Healthcare | D5: 2nd Floor | E5: E-201 | F5: Electrical Room | G5: Full Building | H5: XFMR-001 | I5: XFMR-1 | J5: Square D | K5: EX75T3HCU | L5: 9827A44821 | M5: 2005 | N5: Discoloration on secondary terminals. NETA test recommended. | O5: 2 | P5: Dry Type Transformer | Q5: 75 kVA / 480-208Y/120V | R5: 1 | S5: EA | T5: Replace | U5: D50 Electrical | V5: 35 | W5: =M5+V5 | X5: =W5-2026 | Y5: 1 | Z5: 2027 | AA5: 20000 | AB5: =R5*AA5 | AC5: =IF(35>0,AB5*MAX(0,X5)/35,0) | AD5: =AB5*0.01 | AE5: 85000 | AF5: 2026-06-25 | AG5: 5 | AH5: 1
A6: 02 | B6: Riverside Medical Center | C6: Healthcare | D6: 2nd Floor | E6: E-201 | F6: Electrical Room | G6: Critical Life Safety Circuit | H6: GENSET-001 | I6: GENSET-1 | J6: Cummins | K6: C500D6R | L6: J-100012245 | M6: 2018 | N6: Load bank test 2025-11. Transfer time within spec. | O6: 5 | P6: Emergency Generator | Q6: 500 kW / 480V | R6: 1 | S6: EA | T6: Maintain | U6: D50 Electrical | V6: 25 | W6: =M6+V6 | X6: =W6-2026 | Y6: 17 | Z6: 2043 | AA6: 60000 | AB6: =R6*AA6 | AC6: =IF(25>0,AB6*MAX(0,X6)/25,0) | AD6: =AB6*0.04 | AE6: 85000 | AF6: 2026-06-25 | AG6: 5 | AH6: 2
A7: 01 | B7: Riverside Medical Center | C7: Healthcare | D7: Basement | E7: B-105 | F7: Domestic Water Room | G7: Building-Wide DHW | H7: WH-001 | I7: WH-1 | J7: A.O. Smith | K7: BTXL-120-ASME | L7: AOS-190874621 | M7: 2017 | N7: Sacrificial anode condition unknown. Schedule service. | O7: 3 | P7: Commercial Water Heater | Q7: 120 Gal / 300 MBH | R7: 3 | S7: EA | T7: Maintain | U7: D20 Plumbing | V7: 15 | W7: =M7+V7 | X7: =W7-2026 | Y7: 6 | Z7: 2032 | AA7: 9500 | AB7: =R7*AA7 | AC7: =IF(15>0,AB7*MAX(0,X7)/15,0) | AD7: =AB7*0.025 | AE7: 85000 | AF7: 2026-06-25 | AG7: 4 | AH7: 2
A8: 01 | B8: Riverside Medical Center | C8: Healthcare | D8: Basement | E8: B-110 | F8: Fire Pump Room | G8: Sprinkler System – Full Building | H8: FP-001 | I8: FP-1 | J8: Peerless | K8: AE4AE-20 | L8: PRL-20172271 | M8: 2010 | N8: Annual fire pump test passed. Packing gland drips slightly. | O8: 4 | P8: Fire Pump | Q8: 750 GPM @ 100 PSI | R8: 1 | S8: EA | T8: Maintain | U8: D40 Fire Protection | V8: 20 | W8: =M8+V8 | X8: =W8-2026 | Y8: 4 | Z8: 2030 | AA8: 20000 | AB8: =R8*AA8 | AC8: =IF(20>0,AB8*MAX(0,X8)/20,0) | AD8: =AB8*0.03 | AE8: 85000 | AF8: 2026-06-25 | AG8: 5 | AH8: 1
A9: 01 | B9: Riverside Medical Center | C9: Healthcare | D9: 1st Floor | E9: 112 | F9: Fire Command Center | G9: Campus-Wide Life Safety | H9: FACP-001 | I9: FACP-1 | J9: Notifier | K9: NFS2-3030 | L9: NTF-20091188 | M9: 2009 | N9: Firmware out of support. Six zone cards showing supervisory fault. | O9: 2 | P9: Fire Alarm Control Panel | Q9: 3030 Points | R9: 1 | S9: EA | T9: Replace | U9: D40 Fire Protection | V9: 15 | W9: =M9+V9 | X9: =W9-2026 | Y9: 0 | Z9: 2026 | AA9: 14000 | AB9: =R9*AA9 | AC9: =IF(15>0,AB9*MAX(0,X9)/15,0) | AD9: =AB9*0.04 | AE9: 85000 | AF9: 2026-06-25 | AG9: 5 | AH9: 1
A10: TOTALS / PORTFOLIO SUMMARY | AB10: =SUM(AB2:AB9) | AC10: =SUM(AC2:AC9) | AD10: =SUM(AD2:AD9)

Sheet output-capX
A1: Inflation Rate: | B1: 0.05
A2: Facility Name | B2: NPV (30 Yr) | C2: Year. 1 | D2: Year. 2 | E2: Year. 3 | F2: Year. 4 | G2: Year. 5 | H2: Year. 6 | I2: Year. 7 | J2: Year. 8 | K2: Year. 9 | L2: Year. 10 | M2: Year. 11 | N2: Year. 12 | O2: Year. 13 | P2: Year. 14 | Q2: Year. 15 | R2: Year. 16 | S2: Year. 17 | T2: Year. 18 | U2: Year. 19 | V2: Year. 20 | W2: Year. 21 | X2: Year. 22 | Y2: Year. 23 | Z2: Year. 24 | AA2: Year. 25 | AB2: Year. 26 | AC2: Year. 27 | AD2: Year. 28 | AE2: Year. 29 | AF2: Year. 30
A3: Riverside Medical Center | B3: =SUM(C3:AF3) | C3: =SUMPRODUCT(('Zonelark FCA Log'!$B$2:$B$9=$A3)*('Zonelark FCA Log'!$Z$2:$Z$9=2027)*'Zonelark FCA Log'!$AB$2:$AB$9)*(1+$B$1)^1 | D3: =SUMPRODUCT(('Zonelark FCA Log'!$B$2:$B$9=$A3)*('Zonelark FCA Log'!$Z$2:$Z$9=2028)*'Zonelark FCA Log'!$AB$2:$AB$9)*(1+$B$1)^2 | E3: =SUMPRODUCT(('Zonelark FCA Log'!$B$2:$B$9=$A3)*('Zonelark FCA Log'!$Z$2:$Z$9=2029)*'Zonelark FCA Log'!$AB$2:$AB$9)*(1+$B$1)^3 | F3: =SUMPRODUCT(('Zonelark FCA Log'!$B$2:$B$9=$A3)*('Zonelark FCA Log'!$Z$2:$Z$9=2030)*'Zonelark FCA Log'!$AB$2:$AB$9)*(1+$B$1)^4 | G3: =SUMPRODUCT(('Zonelark FCA Log'!$B$2:$B$9=$A3)*('Zonelark FCA Log'!$Z$2:$Z$9=2031)*'Zonelark FCA Log'!$AB$2:$AB$9)*(1+$B$1)^5 | H3: =SUMPRODUCT(('Zonelark FCA Log'!$B$2:$B$9=$A3)*('Zonelark FCA Log'!$Z$2:$Z$9=2032)*'Zonelark FCA Log'!$AB$2:$AB$9)*(1+$B$1)^6 | I3: =SUMPRODUCT(('Zonelark FCA Log'!$B$2:$B$9=$A3)*('Zonelark FCA Log'!$Z$2:$Z$9=2033)*'Zonelark FCA Log'!$AB$2:$AB$9)*(1+$B$1)^7 | J3: =SUMPRODUCT(('Zonelark FCA Log'!$B$2:$B$9=$A3)*('Zonelark FCA Log'!$Z$2:$Z$9=2034)*'Zonelark FCA Log'!$AB$2:$AB$9)*(1+$B$1)^8 | K3: =SUMPRODUCT(('Zonelark FCA Log'!$B$2:$B$9=$A3)*('Zonelark FCA Log'!$Z$2:$Z$9=2035)*'Zonelark FCA Log'!$AB$2:$AB$9)*(1+$B$1)^9 | L3: =SUMPRODUCT(('Zonelark FCA Log'!$B$2:$B$9=$A3)*('Zonelark FCA Log'!$Z$2:$Z$9=2036)*'Zonelark FCA Log'!$AB$2:$AB$9)*(1+$B$1)^10 | M3: =SUMPRODUCT(('Zonelark FCA Log'!$B$2:$B$9=$A3)*('Zonelark FCA Log'!$Z$2:$Z$9=2037)*'Zonelark FCA Log'!$AB$2:$AB$9)*(1+$B$1)^11 | N3: =SUMPRODUCT(('Zonelark FCA Log'!$B$2:$B$9=$A3)*('Zonelark FCA Log'!$Z$2:$Z$9=2038)*'Zonelark FCA Log'!$AB$2:$AB$9)*(1+$B$1)^12 | O3: =SUMPRODUCT(('Zonelark FCA Log'!$B$2:$B$9=$A3)*('Zonelark FCA Log'!$Z$2:$Z$9=2039)*'Zonelark FCA Log'!$AB$2:$AB$9)*(1+$B$1)^13 | P3: =SUMPRODUCT(('Zonelark FCA Log'!$B$2:$B$9=$A3)*('Zonelark FCA Log'!$Z$2:$Z$9=2040)*'Zonelark FCA Log'!$AB$2:$AB$9)*(1+$B$1)^14 | Q3: =SUMPRODUCT(('Zonelark FCA Log'!$B$2:$B$9=$A3)*('Zonelark FCA Log'!$Z$2:$Z$9=2041)*'Zonelark FCA Log'!$AB$2:$AB$9)*(1+$B$1)^15 | R3: =SUMPRODUCT(('Zonelark FCA Log'!$B$2:$B$9=$A3)*('Zonelark FCA Log'!$Z$2:$Z$9=2042)*'Zonelark FCA Log'!$AB$2:$AB$9)*(1+$B$1)^16 | S3: =SUMPRODUCT(('Zonelark FCA Log'!$B$2:$B$9=$A3)*('Zonelark FCA Log'!$Z$2:$Z$9=2043)*'Zonelark FCA Log'!$AB$2:$AB$9)*(1+$B$1)^17 | T3: =SUMPRODUCT(('Zonelark FCA Log'!$B$2:$B$9=$A3)*('Zonelark FCA Log'!$Z$2:$Z$9=2044)*'Zonelark FCA Log'!$AB$2:$AB$9)*(1+$B$1)^18 | U3: =SUMPRODUCT(('Zonelark FCA Log'!$B$2:$B$9=$A3)*('Zonelark FCA Log'!$Z$2:$Z$9=2045)*'Zonelark FCA Log'!$AB$2:$AB$9)*(1+$B$1)^19 | V3: =SUMPRODUCT(('Zonelark FCA Log'!$B$2:$B$9=$A3)*('Zonelark FCA Log'!$Z$2:$Z$9=2046)*'Zonelark FCA Log'!$AB$2:$AB$9)*(1+$B$1)^20 | W3: =SUMPRODUCT(('Zonelark FCA Log'!$B$2:$B$9=$A3)*('Zonelark FCA Log'!$Z$2:$Z$9=2047)*'Zonelark FCA Log'!$AB$2:$AB$9)*(1+$B$1)^21 | X3: =SUMPRODUCT(('Zonelark FCA Log'!$B$2:$B$9=$A3)*('Zonelark FCA Log'!$Z$2:$Z$9=2048)*'Zonelark FCA Log'!$AB$2:$AB$9)*(1+$B$1)^22 | Y3: =SUMPRODUCT(('Zonelark FCA Log'!$B$2:$B$9=$A3)*('Zonelark FCA Log'!$Z$2:$Z$9=2049)*'Zonelark FCA Log'!$AB$2:$AB$9)*(1+$B$1)^23 | Z3: =SUMPRODUCT(('Zonelark FCA Log'!$B$2:$B$9=$A3)*('Zonelark FCA Log'!$Z$2:$Z$9=2050)*'Zonelark FCA Log'!$AB$2:$AB$9)*(1+$B$1)^24 | AA3: =SUMPRODUCT(('Zonelark FCA Log'!$B$2:$B$9=$A3)*('Zonelark FCA Log'!$Z$2:$Z$9=2051)*'Zonelark FCA Log'!$AB$2:$AB$9)*(1+$B$1)^25 | AB3: =SUMPRODUCT(('Zonelark FCA Log'!$B$2:$B$9=$A3)*('Zonelark FCA Log'!$Z$2:$Z$9=2052)*'Zonelark FCA Log'!$AB$2:$AB$9)*(1+$B$1)^26 | AC3: =SUMPRODUCT(('Zonelark FCA Log'!$B$2:$B$9=$A3)*('Zonelark FCA Log'!$Z$2:$Z$9=2053)*'Zonelark FCA Log'!$AB$2:$AB$9)*(1+$B$1)^27 | AD3: =SUMPRODUCT(('Zonelark FCA Log'!$B$2:$B$9=$A3)*('Zonelark FCA Log'!$Z$2:$Z$9=2054)*'Zonelark FCA Log'!$AB$2:$AB$9)*(1+$B$1)^28 | AE3: =SUMPRODUCT(('Zonelark FCA Log'!$B$2:$B$9=$A3)*('Zonelark FCA Log'!$Z$2:$Z$9=2055)*'Zonelark FCA Log'!$AB$2:$AB$9)*(1+$B$1)^29 | AF3: =SUMPRODUCT(('Zonelark FCA Log'!$B$2:$B$9=$A3)*('Zonelark FCA Log'!$Z$2:$Z$9=2056)*'Zonelark FCA Log'!$AB$2:$AB$9)*(1+$B$1)^30
A4: TOTAL — ALL FACILITIES | B4: =SUM(B3:B3) | C4: =SUM(C3:C3) | D4: =SUM(D3:D3) | E4: =SUM(E3:E3) | F4: =SUM(F3:F3) | G4: =SUM(G3:G3) | H4: =SUM(H3:H3) | I4: =SUM(I3:I3) | ... AF4: =SUM(AF3:AF3)
